lakersin5/aes.py
lakersin5/aes_nolib.py
lakersin5/des.py
lakersin5/des_nolib.py
lakersin5/ds.py
lakersin5/ecc.py
lakersin5/ecc_encryption.py
lakersin5/ecc_signature.py
lakersin5/ecdsa.py
lakersin5/elgamal-ds.py
lakersin5/elgamal.py
lakersin5/elgamal_encryption.py
lakersin5/elgamal_signature.py
lakersin5/intro.py
lakersin5/legendre_symbol.py
lakersin5/paillier.py
lakersin5/pointadd.py
lakersin5/pointdbl.py
lakersin5/primality.py
lakersin5/rabin.py
lakersin5/rabin_cryptosystem.py
lakersin5/rsa-homo.py
lakersin5/rsa.py
lakersin5/rsa_encryption.py
lakersin5/rsa_signature.py
lakersin5/simplified_des.py
lakersin5/cheatsheet/cheatsheet.txt
lakersin5-1.0.1.dist-info/METADATA
lakersin5-1.0.1.dist-info/WHEEL
lakersin5-1.0.1.dist-info/top_level.txt
lakersin5-1.0.1.dist-info/RECORD
