Metadata-Version: 2.4
Name: lakersin5
Version: 1.0.1
Summary: Pure Python cryptographic algorithms and cybersecurity command cheatsheets.
Author-email: lebron <youremail@example.com>
License: MIT
Keywords: cryptography,cybersecurity,python,algorithms
Classifier: Programming Language :: Python :: 3
Classifier: License :: OSI Approved :: MIT License
Classifier: Operating System :: OS Independent
Classifier: Topic :: Security :: Cryptography
Requires-Python: >=3.6
